MANIFEST.in
README.md
setup.py
devil/__init__.py
devil/auth.py
devil/datamapper.py
devil/errors.py
devil/http.py
devil/resource.py
devil/util.py
devil.egg-info/PKG-INFO
devil.egg-info/SOURCES.txt
devil.egg-info/dependency_links.txt
devil.egg-info/requires.txt
devil.egg-info/top_level.txt
devil/fields/__init__.py
devil/fields/factory.py
devil/fields/fields.py
devil/fields/representation.py
devil/mappers/__init__.py
devil/mappers/jsonmapper.py
devil/mappers/xmlmapper.py
devil/perm/__init__.py
devil/perm/acl.py
devil/perm/management.py