Metadata-Version: 1.0
Name: devil
Version: 0.9
Summary: Simple REST framework for Django
Home-page: https://github.com/wuher/devil/
Author: Janne Kuuskeri (wuher)
Author-email: janne.kuuskeri@gmail.com
License: MIT
Platform: UNKNOWN
